MANIFEST.in
README.rst
setup.py
comuneimola/__init__.py
comuneimola.compensi.egg-info/PKG-INFO
comuneimola.compensi.egg-info/SOURCES.txt
comuneimola.compensi.egg-info/dependency_links.txt
comuneimola.compensi.egg-info/entry_points.txt
comuneimola.compensi.egg-info/namespace_packages.txt
comuneimola.compensi.egg-info/not-zip-safe
comuneimola.compensi.egg-info/requires.txt
comuneimola.compensi.egg-info/top_level.txt
comuneimola/compensi/README.txt
comuneimola/compensi/__init__.py
comuneimola/compensi/build_18n_po.sh
comuneimola/compensi/config.py
comuneimola/compensi/configure.zcml
comuneimola/compensi/utilities.py
comuneimola/compensi/validators.py
comuneimola/compensi/browser/__init__.py
comuneimola/compensi/browser/configure.zcml
comuneimola/compensi/browser/translation.py
comuneimola/compensi/browser/vistaareacompensiview.pt
comuneimola/compensi/browser/vistaareacompensiview.py
comuneimola/compensi/browser/vistacompensoview.pt
comuneimola/compensi/browser/vistacompensoview.py
comuneimola/compensi/browser/css/comuneimola_compensi.css
comuneimola/compensi/browser/css/dataTableFix.css
comuneimola/compensi/browser/csv_export/__init__.py
comuneimola/compensi/browser/csv_export/configure.zcml
comuneimola/compensi/browser/csv_export/export_documents.py
comuneimola/compensi/browser/images/areacompensi.png
comuneimola/compensi/browser/images/compensi.png
comuneimola/compensi/browser/javascript/areacompensi.js
comuneimola/compensi/content/__init__.py
comuneimola/compensi/content/atareacompensi.py
comuneimola/compensi/content/atcompenso.py
comuneimola/compensi/content/atlinkcompenso.py
comuneimola/compensi/content/configure.zcml
comuneimola/compensi/interfaces/__init__.py
comuneimola/compensi/interfaces/atareacompensi.py
comuneimola/compensi/interfaces/atcompenso.py
comuneimola/compensi/interfaces/atlinkcompenso.py
comuneimola/compensi/locales/compensi.collective.js.datatables.pot
comuneimola/compensi/locales/comuneimola.compensi.pot
comuneimola/compensi/locales/manual.pot
comuneimola/compensi/locales/it/LC_MESSAGES/compensi.collective.js.datatables.po
comuneimola/compensi/locales/it/LC_MESSAGES/comuneimola.compensi.po
comuneimola/compensi/profiles/default/catalog.xml
comuneimola/compensi/profiles/default/cssregistry.xml
comuneimola/compensi/profiles/default/factorytool.xml
comuneimola/compensi/profiles/default/metadata.xml
