Metadata-Version: 1.1
Name: comuneimola.compensi
Version: 1.1
Summary: Gestione Compensi per il comune di Imola
Home-page: http://plone.org/products/comuneimola.compensi
Author: RedTurtle Technology
Author-email: sviluppoplone@redturtle.it
License: GPL
Keywords: Art18 DL 83/2012 compensi comuneimola
Platform: UNKNOWN
Classifier: Framework :: Plone
Classifier: Framework :: Plone :: 3.3
Classifier: Framework :: Plone :: 4.0
Classifier: Framework :: Plone :: 4.1
Classifier: Framework :: Plone :: 4.2
Classifier: Programming Language :: Python :: 2
Classifier: Intended Audience :: Developers
Classifier: License :: OSI Approved :: GNU General Public License (GPL)
